jinjarecurse/main.py
Jinja_Recurse-0.0.1.dist-info/LICENSE
Jinja_Recurse-0.0.1.dist-info/METADATA
Jinja_Recurse-0.0.1.dist-info/WHEEL
Jinja_Recurse-0.0.1.dist-info/entry_points.txt
Jinja_Recurse-0.0.1.dist-info/top_level.txt
Jinja_Recurse-0.0.1.dist-info/RECORD
