Metadata-Version: 2.1
Name: Jinja-Recurse
Version: 0.0.1
Summary: Jinja Recursive Templating from the CLI
Home-page: https://www.github.com/diginc/jinjarecurse
Author: diginc
Author-email: adam@diginc.us
License: MIT
Keywords: jinja templater
Platform: UNKNOWN
Classifier: Development Status :: 3 - Alpha
Classifier: Topic :: Utilities
Classifier: License :: OSI Approved :: MIT License
Requires-Dist: docopt (==0.6.2)
Requires-Dist: jinja2 (==2.11.2)
Requires-Dist: markupsafe (==1.1.1)
Requires-Dist: pathlib2 (==2.3.5)
Requires-Dist: pyyaml (==5.3.1)
Requires-Dist: six (==1.15.0)
